pasiphae/__init__.py
pasiphae/__main__.py
pasiphae/cli.py
pasiphae/domain.py
pasiphae/file.py
pasiphae/py.typed
pasiphae/resolvers.py
pasiphae/to_python_type.py
pasiphae/tools.py
pasiphae/types.py
pasiphae-0.0.4.dist-info/entry_points.txt
pasiphae-0.0.4.dist-info/WHEEL
pasiphae-0.0.4.dist-info/METADATA
pasiphae-0.0.4.dist-info/RECORD
